odoo9_addon_cms_notification-9.0.1.0.0.99.dev2-py2.7-nspkg.pth
odoo9_addon_cms_notification-9.0.1.0.0.99.dev2.dist-info/DESCRIPTION.rst
odoo9_addon_cms_notification-9.0.1.0.0.99.dev2.dist-info/METADATA
odoo9_addon_cms_notification-9.0.1.0.0.99.dev2.dist-info/RECORD
odoo9_addon_cms_notification-9.0.1.0.0.99.dev2.dist-info/WHEEL
odoo9_addon_cms_notification-9.0.1.0.0.99.dev2.dist-info/metadata.json
odoo9_addon_cms_notification-9.0.1.0.0.99.dev2.dist-info/namespace_packages.txt
odoo9_addon_cms_notification-9.0.1.0.0.99.dev2.dist-info/top_level.txt
odoo_addons/cms_notification/README.rst
odoo_addons/cms_notification/__init__.py
odoo_addons/cms_notification/__openerp__.py
odoo_addons/cms_notification/controllers/__init__.py
odoo_addons/cms_notification/controllers/main.py
odoo_addons/cms_notification/i18n/de.po
odoo_addons/cms_notification/i18n/fr.po
odoo_addons/cms_notification/i18n/hi_IN.po
odoo_addons/cms_notification/images/cms_notif_listing.png
odoo_addons/cms_notification/images/cms_notif_menu.png
odoo_addons/cms_notification/images/cms_notif_settings.png
odoo_addons/cms_notification/models/__init__.py
odoo_addons/cms_notification/models/mail_message.py
odoo_addons/cms_notification/models/mail_message_subtype.py
odoo_addons/cms_notification/models/notification_listing.py
odoo_addons/cms_notification/models/notification_panel_form.py
odoo_addons/cms_notification/models/res_users.py
odoo_addons/cms_notification/models/test_models.py
odoo_addons/cms_notification/models/widget.py
odoo_addons/cms_notification/static/description/icon.png
odoo_addons/cms_notification/static/src/js/read_unread.js
odoo_addons/cms_notification/static/src/less/styles.less
odoo_addons/cms_notification/templates/assets.xml
odoo_addons/cms_notification/templates/help_msg.xml
odoo_addons/cms_notification/templates/notification_listing.xml
odoo_addons/cms_notification/templates/user_menu.xml
odoo_addons/cms_notification/templates/widget.xml
odoo_addons/cms_notification/tests/__init__.py
odoo_addons/cms_notification/tests/test_notifications.py
odoo_addons/cms_notification/views/mail_message_subtype_views.xml
