Metadata-Version: 2.0
Name: odoo9-addon-cms-notification
Version: 9.0.1.0.0.99.dev2
Summary: Basic notifications management for your CMS system
Home-page: UNKNOWN
Author: Camptocamp,Odoo Community Association (OCA)
Author-email: support@odoo-community.org
License: LGPL-3
Platform: UNKNOWN
Classifier: Programming Language :: Python
Classifier: Framework :: Odoo
Classifier: License :: OSI Approved :: GNU Lesser General Public License v3 (LGPLv3)
Requires-Python: ~=2.7
Requires-Dist: odoo (<9.1a,>=9.0a)
Requires-Dist: odoo9-addon-base-fontawesome
Requires-Dist: odoo9-addon-cms-form
Requires-Dist: odoo9-addon-mail-digest
